atlas_rag/__init__.py
atlas_rag/billion/__init__.py
atlas_rag/billion/neo4j_api.py
atlas_rag/billion/prompt_template.py
atlas_rag/billion/retreiver.py
atlas_rag/evaluation/__init__.py
atlas_rag/evaluation/benchmark.py
atlas_rag/evaluation/evaluation.py
atlas_rag/evaluation/util.py
atlas_rag/kg_construction/concept_generation.py
atlas_rag/kg_construction/triple_extraction.py
atlas_rag/reader/__init__.py
atlas_rag/reader/llm_generator.py
atlas_rag/retriever/__init__.py
atlas_rag/retriever/embedding_model.py
atlas_rag/retriever/filter_template.py
atlas_rag/retriever/indexer.py
atlas_rag/retriever/rag_model.py
atlas_rag/retriever/rag_qa_prompt.py
atlas_rag/utils/__init__.py
atlas_rag/utils/compute_embedding.py
atlas_rag/utils/concept_to_csv.py
atlas_rag/utils/convert_csv2npy.py
atlas_rag/utils/convert_json2graphml.py
atlas_rag/utils/create_index.py
atlas_rag/utils/csv_add_column.py
atlas_rag/utils/csv_to_graphml.py
atlas_rag/utils/json_2_csv.py
atlas_rag/utils/json_repair.py
atlas_rag/utils/merge_csv.py
atlas_rag/utils/triple_generator.py
atlas_rag/utils/utils.py
atlas_rag-2025.0.0.dist-info/WHEEL
atlas_rag-2025.0.0.dist-info/METADATA
atlas_rag-2025.0.0.dist-info/RECORD
