Metadata-Version: 2.4
Name: atlas-rag
Version: 2025.0.0
Summary: AutoSchemaKG, a framework for fully autonomous knowledge graph construction that eliminates the need for predefined schemas.
Keywords: retrieval-augmented-generation,knowledge-graph,nlp
Author-email: Jiaxin Bai <jbai@connect.ust.hk>, Hong Ting TSANG <httsangaj@connect.ust.hk>, Haoyu Huang <haoyuhuang@link.cuhk.edu.hk>
Requires-Python: >=3.9
Classifier: Programming Language :: Python
Classifier: Programming Language :: Python :: 3.9
Classifier: Programming Language :: Python :: 3.10
Classifier: Programming Language :: Python :: 3.11
Classifier: Programming Language :: Python :: 3.12
Classifier: Programming Language :: Python :: 3 :: Only
Requires-Dist: numpy>=1.26.0, <2.0.0
Requires-Dist: networkx>=3.1
Requires-Dist: tqdm>=4.65.0
Requires-Dist: jsonschema>=4.17.3
Requires-Dist: neo4j>=5.8.0
Requires-Dist: fastapi>=0.95.0
Requires-Dist: uvicorn>=0.21.0
Requires-Dist: openai>=1.0.0
Requires-Dist: tenacity>=8.2.0
Requires-Dist: pandas>=2.0.0
Requires-Dist: sentence-transformers>=2.7.0, <=3.0.0
Requires-Dist: transformers>=4.42.4, <=4.45.1
Requires-Dist: datasets
Requires-Dist: einops
Requires-Dist: accelerate>=0.26.0, <=1.7.0
Requires-Dist: nltk
Requires-Dist: graphdatascience
Requires-Dist: torch>=2.5.1 ; extra == "gpu"
Requires-Dist: torchvision>=0.20.1 ; extra == "gpu"
Requires-Dist: torchaudio>=2.5.1 ; extra == "gpu"
Requires-Dist: flash-attn>=2.2.0 ; extra == "gpu"
Provides-Extra: gpu
